ZetcodeNetJiaochengChuyiFix1/README.md
ZetcodeNetJiaochengChuyiFix1/__init__.py
ZetcodeNetJiaochengChuyiFix1/__main__.py
ZetcodeNetJiaochengChuyiFix1/file.epub
ZetcodeNetJiaochengChuyiFix1/index.html
ZetcodeNetJiaochengChuyiFix1/css/__init__.py
ZetcodeNetJiaochengChuyiFix1/css/annotations.css
ZetcodeNetJiaochengChuyiFix1/css/main.css
ZetcodeNetJiaochengChuyiFix1/css/normalize.css
ZetcodeNetJiaochengChuyiFix1/css/popup.css
ZetcodeNetJiaochengChuyiFix1/font/__init__.py
ZetcodeNetJiaochengChuyiFix1/font/fontello.eot
ZetcodeNetJiaochengChuyiFix1/font/fontello.svg
ZetcodeNetJiaochengChuyiFix1/font/fontello.ttf
ZetcodeNetJiaochengChuyiFix1/font/fontello.woff
ZetcodeNetJiaochengChuyiFix1/img/__init__.py
ZetcodeNetJiaochengChuyiFix1/img/annotator-glyph-sprite.png
ZetcodeNetJiaochengChuyiFix1/img/annotator-icon-sprite.png
ZetcodeNetJiaochengChuyiFix1/img/apple-touch-icon.png
ZetcodeNetJiaochengChuyiFix1/img/cancelfullscreen.png
ZetcodeNetJiaochengChuyiFix1/img/close.png
ZetcodeNetJiaochengChuyiFix1/img/fullscreen.png
ZetcodeNetJiaochengChuyiFix1/img/loader.gif
ZetcodeNetJiaochengChuyiFix1/img/menu-icon.png
ZetcodeNetJiaochengChuyiFix1/img/save.png
ZetcodeNetJiaochengChuyiFix1/img/saved.png
ZetcodeNetJiaochengChuyiFix1/img/settings-s.png
ZetcodeNetJiaochengChuyiFix1/img/settings.png
ZetcodeNetJiaochengChuyiFix1/img/star.png
ZetcodeNetJiaochengChuyiFix1/js/__init__.py
ZetcodeNetJiaochengChuyiFix1/js/epub.js
ZetcodeNetJiaochengChuyiFix1/js/epub.min.js
ZetcodeNetJiaochengChuyiFix1/js/epub.min.map
ZetcodeNetJiaochengChuyiFix1/js/hooks.min.js
ZetcodeNetJiaochengChuyiFix1/js/hooks.min.map
ZetcodeNetJiaochengChuyiFix1/js/reader.js
ZetcodeNetJiaochengChuyiFix1/js/reader.js.map
ZetcodeNetJiaochengChuyiFix1/js/reader.min.js
ZetcodeNetJiaochengChuyiFix1/js/reader.min.map
ZetcodeNetJiaochengChuyiFix1/js/hooks/__init__.py
ZetcodeNetJiaochengChuyiFix1/js/hooks/extensions/__init__.py
ZetcodeNetJiaochengChuyiFix1/js/hooks/extensions/highlight.js
zetcode_net_jiaocheng_chuyi_fix1-2025.3.24.1.dist-info/METADATA
zetcode_net_jiaocheng_chuyi_fix1-2025.3.24.1.dist-info/WHEEL
zetcode_net_jiaocheng_chuyi_fix1-2025.3.24.1.dist-info/entry_points.txt
zetcode_net_jiaocheng_chuyi_fix1-2025.3.24.1.dist-info/top_level.txt
zetcode_net_jiaocheng_chuyi_fix1-2025.3.24.1.dist-info/RECORD
